CHANGELOG.rst
LICENSE.txt
MANIFEST.in
NOTES.txt
README.rst
VERSION.txt
setup.cfg
setup.py
parsedifflib/__init__.py
parsedifflib/api.py
parsedifflib/cli.py
parsedifflib/parser.py
parsedifflib/test.py
parsedifflib/util.py
parsedifflib.egg-info/PKG-INFO
parsedifflib.egg-info/SOURCES.txt
parsedifflib.egg-info/dependency_links.txt
parsedifflib.egg-info/entry_points.txt
parsedifflib.egg-info/requires.txt
parsedifflib.egg-info/top_level.txt
parsedifflib.egg-info/zip-safe
parsedifflib/data/svnlook-empty-file-only.diff
parsedifflib/data/svnlook-empty-file-only.diff.output.reference
parsedifflib/data/svnlook-empty-file.diff
parsedifflib/data/svnlook-empty-file.diff.output.reference
parsedifflib/data/svnlook-property-changes.diff
parsedifflib/data/svnlook-property-changes.diff.output.reference
parsedifflib/data/svnlook.diff
parsedifflib/data/svnlook.diff.output.reference