Metadata-Version: 1.1
Name: parsedifflib
Version: 0.2.0
Summary: A universal "diff" patch parsing library.
Home-page: http://github.com/metagriffin/parsedifflib
Author: metagriffin
Author-email: mg.pypi@metagriffin.net
License: GPLv3+
Keywords: universal diff parse patch
Platform: any
Classifier: Development Status :: 1 - Planning
Classifier: Intended Audience :: Developers
Classifier: Programming Language :: Python
Classifier: Operating System :: OS Independent
Classifier: Natural Language :: English
Classifier: License :: OSI Approved :: GNU General Public License v3 or later (GPLv3+)
